syntrac/sdk/.DS_Store
syntrac/sdk/__init__.py
syntrac/sdk/config/__init__.py
syntrac/sdk/decorators/__init__.py
syntrac/sdk/decorators/helper.py
syntrac/sdk/decorators/task.py
syntrac/sdk/decorators/workflow.py
syntrac/sdk/fetcher.py
syntrac/sdk/instruments.py
syntrac/sdk/metrics/__init__.py
syntrac/sdk/metrics/metrics.py
syntrac/sdk/otlp/json/__init__.py
syntrac/sdk/otlp/json/trace_exporter/__init__.py
syntrac/sdk/otlp/json/version.py
syntrac/sdk/telemetry.py
syntrac/sdk/tracing/.DS_Store
syntrac/sdk/tracing/__init__.py
syntrac/sdk/tracing/content_allow_list.py
syntrac/sdk/tracing/context.py
syntrac/sdk/tracing/context_manager.py
syntrac/sdk/tracing/context_passing.py
syntrac/sdk/tracing/span_from_context.py
syntrac/sdk/tracing/tracing.py
syntrac/sdk/utils/__init__.py
syntrac/sdk/utils/in_memory_span_exporter.py
syntrac/sdk/version.py
syntrac_sdk-0.0.12.dist-info/METADATA
syntrac_sdk-0.0.12.dist-info/WHEEL
syntrac_sdk-0.0.12.dist-info/RECORD
