Metadata-Version: 2.1
Name: syntrac-sdk
Version: 0.0.12
Summary: Syntrac Software Development Kit (SDK) for Python
Home-page: https://github.com/syntracAI/syntrac
License: Apache-2.0
Author: Vuong Ngo
Author-email: vuongngo.pd@gmail.com
Requires-Python: >=3.9,<4
Classifier: License :: OSI Approved :: Apache Software License
Classifier: Programming Language :: Python :: 3
Classifier: Programming Language :: Python :: 3.9
Classifier: Programming Language :: Python :: 3.10
Classifier: Programming Language :: Python :: 3.11
Classifier: Programming Language :: Python :: 3.12
Requires-Dist: colorama (>=0.4.6,<0.5.0)
Requires-Dist: deprecated (>=1.2.14,<2.0.0)
Requires-Dist: jinja2 (>=3.1.2,<4.0.0)
Requires-Dist: opentelemetry-api (>=1.23.0,<2.0.0)
Requires-Dist: opentelemetry-exporter-otlp-proto-http (>=1.20.0,<2.0.0)
Requires-Dist: opentelemetry-instrumentation-requests (==0.44b0)
Requires-Dist: opentelemetry-instrumentation-sqlalchemy (==0.44b0)
Requires-Dist: opentelemetry-instrumentation-urllib3 (==0.44b0)
Requires-Dist: opentelemetry-sdk (>=1.20.0,<2.0.0)
Requires-Dist: posthog (>=3.0.2,<4.0.0)
Requires-Dist: pydantic (>=1)
Requires-Dist: syntrac-opentelemetry-instrumentation-anthropic (==0.0.2)
Requires-Dist: syntrac-opentelemetry-instrumentation-bedrock (==0.0.2)
Requires-Dist: syntrac-opentelemetry-instrumentation-chromadb (==0.0.2)
Requires-Dist: syntrac-opentelemetry-instrumentation-cohere (==0.0.2)
Requires-Dist: syntrac-opentelemetry-instrumentation-haystack (==0.0.2)
Requires-Dist: syntrac-opentelemetry-instrumentation-langchain (==0.0.4)
Requires-Dist: syntrac-opentelemetry-instrumentation-llamaindex (==0.0.2)
Requires-Dist: syntrac-opentelemetry-instrumentation-openai (==0.0.2)
Requires-Dist: syntrac-opentelemetry-instrumentation-pinecone (==0.0.2)
Requires-Dist: syntrac-opentelemetry-instrumentation-qdrant (==0.0.2)
Requires-Dist: syntrac-opentelemetry-instrumentation-replicate (==0.0.2)
Requires-Dist: syntrac-opentelemetry-instrumentation-transformers (==0.0.2)
Requires-Dist: syntrac-opentelemetry-instrumentation-vertexai (==0.0.2)
Requires-Dist: syntrac-opentelemetry-instrumentation-watsonx (==0.0.2)
Requires-Dist: syntrac-opentelemetry-instrumentation-weaviate (==0.0.2)
Requires-Dist: syntrac-opentelemetry-semantic-conventions-ai (==0.0.1)
Requires-Dist: tenacity (>=8.2.3,<9.0.0)
Requires-Dist: tiktoken (>=0.6.0,<0.7.0)
Project-URL: Documentation, https://syntrac.com/docs/openllmetry
Project-URL: Repository, https://github.com/syntracAI/syntrac
